MANIFEST.in
README.md
requirements.txt
setup.py
nisaba/__init__.py
nisaba/__main__.py
nisaba/cache_maintenance.py
nisaba/configuration_display.py
nisaba/database_display.py
nisaba/database_maintenance.py
nisaba/metadata_display.py
nisaba/scrollframe_builder.py
nisaba/search_display.py
nisaba/taxonomy_display.py
nisaba/tooltip_creation.py
nisaba.egg-info/PKG-INFO
nisaba.egg-info/SOURCES.txt
nisaba.egg-info/dependency_links.txt
nisaba.egg-info/entry_points.txt
nisaba.egg-info/requires.txt
nisaba.egg-info/top_level.txt
nisaba/assets/add.png
nisaba/assets/audio.png
nisaba/assets/audiovisual.png
nisaba/assets/configuration.png
nisaba/assets/database.png
nisaba/assets/delete.png
nisaba/assets/gist.png
nisaba/assets/icon.gif
nisaba/assets/icon.ico
nisaba/assets/image.png
nisaba/assets/minus.png
nisaba/assets/next.png
nisaba/assets/plus.png
nisaba/assets/previous.png
nisaba/assets/refresh.png
nisaba/assets/save.png
nisaba/assets/search.png
nisaba/assets/taxonomy.png
nisaba/assets/text.png
nisaba/assets/uplevel.png
nisaba/assets/users.png
nisaba/config_files/collections/ArchivalDocumentSet.yaml
nisaba/config_files/collections/Book.yaml
nisaba/config_files/collections/BookChapter.yaml
nisaba/config_files/collections/EditedBook.yaml
nisaba/config_files/collections/JournalArticle.yaml
nisaba/config_files/collections/NewspaperIssue.yaml
nisaba/config_files/collections/NewspaperTitle.yaml
nisaba/config_files/collections/SoundRecording.yaml
nisaba/config_files/collections/StandardCollection.yaml
nisaba/config_files/collections/TranslatedBook.yaml
nisaba/config_files/items/Abstract.yaml
nisaba/config_files/items/AudioDocument.yaml
nisaba/config_files/items/Image.yaml
nisaba/config_files/items/NewspaperArticle.yaml
nisaba/config_files/items/Page.yaml
nisaba/config_files/items/PageExtract.yaml
nisaba/config_files/items/Paragraph.yaml
nisaba/config_files/items/StandardItem.yaml
nisaba/config_files/prefixes/prefixes.txt
nisaba/config_files/segments/StandardSegment.yaml
nisaba/config_files/users/UserMetadata.yaml
nisaba/databases/sample_database.json
nisaba/databases/sample_taxonomy.json
nisaba/databases/backups/placeholder
