Metadata-Version: 2.1
Name: nisaba
Version: 0.3.18
Summary: A tool for multi-modal annotation
Home-page: https://github.com/mhbeals/nisaba
Author: M. H. Beals
Author-email: M.H.Beals@lboro.ac.uk
License: AGPLv3
Download-URL: https://github.com/mhbeals/nisaba/archive/0.3.18.tar.gz
Platform: UNKNOWN
Classifier: License :: OSI Approved :: GNU Affero General Public License v3
Classifier: Programming Language :: Python :: 3
Classifier: Programming Language :: Python :: 3.7
